setup.py
django_pyvows/__init__.py
django_pyvows/context.py
django_pyvows/http_helpers.py
django_pyvows/server.py
django_pyvows/settings_manager.py
django_pyvows/version.py
django_pyvows.egg-info/PKG-INFO
django_pyvows.egg-info/SOURCES.txt
django_pyvows.egg-info/dependency_links.txt
django_pyvows.egg-info/requires.txt
django_pyvows.egg-info/top_level.txt
django_pyvows/assertions/__init__.py
django_pyvows/assertions/models.py
django_pyvows/assertions/templates.py
django_pyvows/assertions/urls.py