Metadata-Version: 1.0
Name: django-pyvows
Version: 0.6.2
Summary: django-pyvows are pyvows extensions to django web framework.
Home-page: https://github.com/rafaelcaricio/django-pyvows
Author: Rafael Caricio
Author-email: rafael@caricio.com
License: MIT
Keywords: testing vows test tdd django web
Platform: UNKNOWN
Classifier: Development Status :: 3 - Alpha
Classifier: Intended Audience :: Developers
Classifier: License :: OSI Approved :: MIT License
Classifier: Natural Language :: English
Classifier: Operating System :: MacOS
Classifier: Operating System :: POSIX :: Linux
Classifier: Programming Language :: Python :: 2.6
Classifier: Topic :: Software Development :: Testing
